setup.py
podcast_parser.egg-info/PKG-INFO
podcast_parser.egg-info/SOURCES.txt
podcast_parser.egg-info/dependency_links.txt
podcast_parser.egg-info/requires.txt
podcast_parser.egg-info/top_level.txt
podcast_parser.egg-info/zip-safe
podcastparser/__init__.py
podcastparser/models.py
podcastparser/parser.py