Metadata-Version: 1.0
Name: podcast-parser
Version: 0.0.2
Summary: fast podcast feed parser
Home-page: http://github.com/tapanpandita/podcast-parser/
Author: Tapan Pandita
Author-email: tapan.pandita@gmail.com
License: BSD
Platform: UNKNOWN
